gamesolverlib/__about__.py
gamesolverlib/__init__.py
gamesolverlib/__init__.pyi
gamesolverlib/_wordfinder_lib/wordfinder.py
gamesolverlib/_wordfinder_lib/test_logs/wordfinder_func.txt
gamesolverlib/_wordfinder_lib/test_logs/wordfinder_test.txt
gamesolverlib/_wordfinder_lib/word_files/english_words.txt
gamesolverlib-1.0.0.dist-info/licenses/LICENSE
gamesolverlib-1.0.0.dist-info/METADATA
gamesolverlib-1.0.0.dist-info/WHEEL
gamesolverlib-1.0.0.dist-info/entry_points.txt
gamesolverlib-1.0.0.dist-info/top_level.txt
gamesolverlib-1.0.0.dist-info/RECORD
