Metadata-Version: 2.4
Name: gamesolverlib
Version: 1.0.0
Summary: Generate valid English word sets based on a specified word length and a set of input characters using anagrams and a file with English words.
Author: Sharrrkkk
Maintainer: Sharrrkkk
License-Expression: MIT
Project-URL: Homepage, https://github.com/Sharrrkkk/game_solver_lib
Project-URL: Documentation, https://github.com/Sharrrkkk/game_solver_lib#README.md
Project-URL: Repository, https://github.com/Sharrrkkk/game_solver_lib
Project-URL: Issues, https://github.com/Sharrrkkk/game_solver_lib/issues
Keywords: anagram,anagrams,game,games,generate,word,words,solver,finder
Classifier: Development Status :: 5 - Production/Stable
Classifier: Intended Audience :: Education
Classifier: Intended Audience :: Developers
Classifier: Topic :: Education
Classifier: Topic :: Software Development
Classifier: Topic :: Software Development :: Build Tools
Classifier: Topic :: Software Development :: Libraries :: Python Modules
Classifier: Topic :: Games/Entertainment
Classifier: Programming Language :: Python :: 3
Requires-Python: >=3.10
License-File: LICENSE
Dynamic: license-file
